social-watcher/__init__.py
social-watcher/cli.py
social-watcher/models.py
social-watcher/watcher.py
social_watcher/__init__.py
social_watcher/cli.py
social_watcher/models.py
social_watcher/watcher.py
social_watcher-0.1.0.dist-info/LICENSE
social_watcher-0.1.0.dist-info/METADATA
social_watcher-0.1.0.dist-info/WHEEL
social_watcher-0.1.0.dist-info/entry_points.txt
social_watcher-0.1.0.dist-info/top_level.txt
social_watcher-0.1.0.dist-info/RECORD
