Metadata-Version: 2.1
Name: social-watcher
Version: 0.1.0
Summary: Social-watcher allow you to watch twitter and instagram profiles.
Home-page: https://github.com/bisguzar/social-watcher
Author: Bugra ISGUZAR
Author-email: ben@bisguzar.com
License: MIT
Platform: UNKNOWN
Classifier: License :: OSI Approved :: MIT License
Classifier: Programming Language :: Python
Classifier: Programming Language :: Python :: 3
Classifier: Programming Language :: Python :: 3.6
Classifier: Programming Language :: Python :: Implementation :: CPython
Classifier: Programming Language :: Python :: Implementation :: PyPy
Requires-Python: >=3.6.0
Requires-Dist: twitter-scraper
Requires-Dist: requests
Requires-Dist: python-telegram-bot
Requires-Dist: pytablewriter
Requires-Dist: peewee
Requires-Dist: click
